chex/__init__.py
chex/chex_test.py
chex/py.typed
chex/_src/__init__.py
chex/_src/asserts.py
chex/_src/asserts_chexify.py
chex/_src/asserts_chexify_test.py
chex/_src/asserts_internal.py
chex/_src/asserts_internal_test.py
chex/_src/asserts_test.py
chex/_src/dataclass.py
chex/_src/dataclass_test.py
chex/_src/dimensions.py
chex/_src/dimensions_test.py
chex/_src/fake.py
chex/_src/fake_set_n_cpu_devices_test.py
chex/_src/fake_test.py
chex/_src/pytypes.py
chex/_src/restrict_backends.py
chex/_src/restrict_backends_test.py
chex/_src/variants.py
chex/_src/variants_test.py
chex/_src/warnings.py
chex/_src/warnings_test.py
chex-0.1.87.dist-info/LICENSE
chex-0.1.87.dist-info/METADATA
chex-0.1.87.dist-info/WHEEL
chex-0.1.87.dist-info/top_level.txt
chex-0.1.87.dist-info/RECORD
