Metadata-Version: 2.1
Name: chex
Version: 0.1.87
Summary: Chex: Testing made fun, in JAX!
Home-page: https://github.com/deepmind/chex
Author: DeepMind
Author-email: chex-dev@google.com
License: Apache 2.0
Keywords: jax testing debugging python machine learning
Classifier: Development Status :: 5 - Production/Stable
Classifier: Environment :: Console
Classifier: Intended Audience :: Science/Research
Classifier: Intended Audience :: Developers
Classifier: License :: OSI Approved :: Apache Software License
Classifier: Operating System :: OS Independent
Classifier: Programming Language :: Python
Classifier: Programming Language :: Python :: 3
Classifier: Topic :: Scientific/Engineering :: Artificial Intelligence
Classifier: Topic :: Software Development :: Testing :: Mocking
Classifier: Topic :: Software Development :: Testing :: Unit
Classifier: Topic :: Software Development :: Libraries :: Python Modules
Requires-Python: >=3.9
License-File: LICENSE
Requires-Dist: absl-py>=0.9.0
Requires-Dist: typing-extensions>=4.2.0
Requires-Dist: jax>=0.4.27
Requires-Dist: jaxlib>=0.4.27
Requires-Dist: numpy>=1.24.1
Requires-Dist: toolz>=0.9.0
Requires-Dist: setuptools; python_version >= "3.12"
